Metadata-Version: 2.1
Name: graphene-neo4j
Version: 2.2.3.9
Summary: Graphene Django-Neo4J (neomodel) integration
Home-page: https://github.com/MardanovTimur/graphene-neo4j
Author: Syrus Akbary; Mardanov Timur
Author-email: timurmardanov97@gmail.com
License: MIT
Keywords: api graphql protocol rest relay graphene
Platform: any
Classifier: Development Status :: 3 - Alpha
Classifier: Intended Audience :: Developers
Classifier: Topic :: Software Development :: Libraries
Classifier: Programming Language :: Python :: 3.6
Classifier: Programming Language :: Python :: Implementation :: PyPy
Requires-Dist: six (>=1.10.0)
Requires-Dist: graphql-core (<3,>=2.1.0)
Requires-Dist: Django (>=1.11)
Requires-Dist: singledispatch (>=3.4.0.3)
Requires-Dist: promise (>=2.1)
Requires-Dist: lazy-import (==0.2.2)
Requires-Dist: neomodel-next (>=3.3.0)
Provides-Extra: test
Requires-Dist: pytest (>=3.6.3) ; extra == 'test'
Requires-Dist: pytest-cov ; extra == 'test'
Requires-Dist: coveralls ; extra == 'test'
Requires-Dist: mock ; extra == 'test'
Requires-Dist: pytz ; extra == 'test'
Requires-Dist: pytest-django (>=3.3.2) ; extra == 'test'
Requires-Dist: django-filter (<2) ; (python_version < "3") and extra == 'test'
